Metadata-Version: 2.3
Name: divyanx-tokenizers
Version: 0.20.0.dev0
Classifier: Development Status :: 5 - Production/Stable
Classifier: Intended Audience :: Developers
Classifier: Intended Audience :: Education
Classifier: Intended Audience :: Science/Research
Classifier: License :: OSI Approved :: Apache Software License
Classifier: Operating System :: OS Independent
Classifier: Programming Language :: Python :: 3
Classifier: Programming Language :: Python :: 3.7
Classifier: Programming Language :: Python :: 3.8
Classifier: Programming Language :: Python :: 3.9
Classifier: Programming Language :: Python :: 3.10
Classifier: Programming Language :: Python :: 3.11
Classifier: Topic :: Scientific/Engineering :: Artificial Intelligence
Requires-Dist: huggingface-hub >=0.16.4, <1.0
Requires-Dist: pytest ; extra == 'testing'
Requires-Dist: requests ; extra == 'testing'
Requires-Dist: numpy ; extra == 'testing'
Requires-Dist: datasets ; extra == 'testing'
Requires-Dist: black ==22.3 ; extra == 'testing'
Requires-Dist: ruff ; extra == 'testing'
Requires-Dist: sphinx ; extra == 'docs'
Requires-Dist: sphinx-rtd-theme ; extra == 'docs'
Requires-Dist: setuptools-rust ; extra == 'docs'
Requires-Dist: tokenizers[testing] ; extra == 'dev'
Provides-Extra: testing
Provides-Extra: docs
Provides-Extra: dev
Keywords: NLP,tokenizer,BPE,transformer,deep learning
Author: Anthony MOI <m.anthony.moi@gmail.com>
Author-email: Divyansh <divyansh.24888@gmail.com>, Anthony Moi <anthony@huggingface.co>
Requires-Python: >=3.7
Project-URL: Homepage, https://github.com/huggingface/tokenizers
Project-URL: Source, https://github.com/huggingface/tokenizers
